hatch_build_scripts/__init__.py
hatch_build_scripts/hooks.py
hatch_build_scripts/plugin.py
hatch_build_scripts/py.typed
hatch_build_scripts-1.0.0.dist-info/METADATA
hatch_build_scripts-1.0.0.dist-info/WHEEL
hatch_build_scripts-1.0.0.dist-info/entry_points.txt
hatch_build_scripts-1.0.0.dist-info/licenses/LICENSE.txt
hatch_build_scripts-1.0.0.dist-info/RECORD
