Metadata-Version: 2.4
Name: hatch_build_scripts
Version: 1.0.0
Summary: Dependency injection without the boilerplate.
Project-URL: Source, https://github.com/rmorshea/hatch-build-scripts
Author-email: Ryan Morshead <ryan.morshead@gmail.com>
License: MIT License
License-File: LICENSE.txt
Classifier: Development Status :: 4 - Beta
Classifier: Programming Language :: Python
Requires-Python: <4,>=3.10
Requires-Dist: hatchling
Requires-Dist: pathspec
